knv_cli/__init__.py
knv_cli/utils.py
knv_cli/api/__init__.py
knv_cli/api/cache.py
knv_cli/api/exceptions.py
knv_cli/api/ola.py
knv_cli/api/webservice.py
knv_cli/cli/__init__.py
knv_cli/cli/cli.py
knv_cli/cli/config.py
knv_cli/cli/database.py
knv_cli/cli/helpers.py
knv_cli/cli/session.py
knv_cli/processors/__init__.py
knv_cli/processors/processor.py
knv_cli/processors/gateways/__init__.py
knv_cli/processors/gateways/gateway.py
knv_cli/processors/gateways/paypal.py
knv_cli/processors/gateways/volksbank.py
knv_cli/processors/knv/__init__.py
knv_cli/processors/knv/infos.py
knv_cli/processors/knv/invoices.py
knv_cli/processors/knv/orders.py
knv_cli/processors/knv/shopkonfigurator.py
knv_cli/processors/knv/expenses/__init__.py
knv_cli/processors/knv/expenses/bwd.py
knv_cli/processors/knv/expenses/edv.py
knv_cli/processors/knv/expenses/sammel.py
knv_cli/processors/knv/revenues/__init__.py
knv_cli/processors/knv/revenues/pcbis.py
knv_cli/processors/knv/revenues/shopkonfigurator.py
knv_cli/structures/__init__.py
knv_cli/structures/endpoint.py
knv_cli/structures/framework.py
knv_cli/structures/shared.py
knv_cli/structures/waypoint.py
knv_cli/structures/invoices/__init__.py
knv_cli/structures/invoices/expense.py
knv_cli/structures/invoices/invoice.py
knv_cli/structures/invoices/invoices.py
knv_cli/structures/invoices/revenue.py
knv_cli/structures/orders/__init__.py
knv_cli/structures/orders/order.py
knv_cli/structures/orders/orders.py
knv_cli/structures/payments/__init__.py
knv_cli/structures/payments/payment.py
knv_cli/structures/payments/payments.py
knv_cli/structures/payments/paypal.py
knv_cli/structures/payments/volksbank.py
knv_cli-0.8.dist-info/LICENSE
knv_cli-0.8.dist-info/METADATA
knv_cli-0.8.dist-info/WHEEL
knv_cli-0.8.dist-info/entry_points.txt
knv_cli-0.8.dist-info/top_level.txt
knv_cli-0.8.dist-info/RECORD
