Metadata-Version: 2.1
Name: knv-cli
Version: 0.8
Summary: Python CLI utility and library for handling data exported from KNV & pcbis.de
Home-page: https://github.com/Fundevogel/knv-tools
Author: Martin Folkers
Author-email: hello@twobrain.io
Maintainer: Fundevogel
Maintainer-email: maschinenraum@fundevogel.de
License: MIT
Project-URL: Source code, https://github.com/Fundevogel/knv-tools
Project-URL: Issues, https://github.com/Fundevogel/knv-tools/issues
Platform: UNKNOWN
Classifier: Development Status :: 4 - Beta
Classifier: Intended Audience :: Developers
Classifier: Intended Audience :: End Users/Desktop
Classifier: License :: OSI Approved :: GNU General Public License v3 (GPLv3)
Classifier: Operating System :: OS Independent
Classifier: Programming Language :: Python :: 3.6
Classifier: Programming Language :: Python :: 3.7
Classifier: Programming Language :: Python :: 3.8
Classifier: Programming Language :: Python :: 3.9
Classifier: Topic :: Office/Business :: Financial :: Accounting
Requires-Python: >=3.6
License-File: LICENSE
Requires-Dist: click
Requires-Dist: isbnlib
Requires-Dist: matplotlib
Requires-Dist: pandas
Requires-Dist: pendulum
Requires-Dist: PyPDF2
Requires-Dist: reportlab
Requires-Dist: xdg
Requires-Dist: zeep
